{
  "version": "1.0.0",
  "last_updated": "2025-01-20",
  "data_source": "knowledge/intent_config.json (意圖分類配置)",
  "intents": [
    {
      "id": "complaint",
      "priority": 1,
      "keywords": ["不滿意", "生氣", "投訴", "抱怨", "很差", "很糟", "後悔"],
      "excludeKeywords": [],
      "contextKeywords": []
    },
    {
      "id": "handoff_to_human",
      "priority": 2,
      "keywords": ["真人", "人工", "客服", "人員", "員工"],
      "excludeKeywords": [],
      "contextKeywords": ["企業", "公司", "團體", "20人", "報價", "合作", "大量"]
    },
    {
      "id": "price_inquiry",
      "priority": 3,
      "keywords": ["多少錢", "價格", "費用", "預算", "價位", "收費", "要多少"],
      "excludeKeywords": ["可以跟我說到", "說到多細", "哪些一定要", "再問真人", "報價範圍"],
      "contextKeywords": []
    },
    {
      "id": "delivery_inquiry",
      "priority": 4,
      "keywords": ["多久會好", "多久收到", "交件時間", "交件", "何時交件", "什麼時候好", "幾天", "交件速度"],
      "excludeKeywords": [],
      "contextKeywords": []
    },
    {
      "id": "location_inquiry",
      "priority": 5,
      "keywords": [
        "地址", "地點", "在哪裡", "在哪", "位置", "怎麼去", "交通", "捷運", 
        "分店", "店址", "停車", "停車場", "停車位", "哪裡停車", "附近停車", 
        "電話", "聯絡電話", "聯繫電話", "電話號碼", "營業時間", "開門時間", 
        "幾點開", "幾點關", "開店時間", "關店時間", "聯絡", "聯繫", "聯絡方式", 
        "聯繫方式", "怎麼聯絡", "怎麼聯繫", "email", "信箱", "ig", "instagram", "line"
      ],
      "excludeKeywords": [],
      "contextKeywords": []
    },
    {
      "id": "makeup_inquiry",
      "priority": 6,
      "keywords": ["妝髮", "化妝", "髮型", "造型", "makeup", "彩妝", "妝容", "髮型設計", "造型師"],
      "excludeKeywords": [],
      "contextKeywords": []
    },
    {
      "id": "booking_inquiry",
      "priority": 7,
      "keywords": ["預約", "改期", "取消", "時間", "時段", "什麼時候", "延後", "提前", "變更", "更改", "調整時間", "重新預約"],
      "excludeKeywords": [],
      "contextKeywords": []
    },
    {
      "id": "comparison",
      "priority": 8,
      "keywords": ["差", "比較", "哪個好", "哪個適合", "有什麼不同", "差別"],
      "excludeKeywords": [],
      "contextKeywords": []
    },
    {
      "id": "goodbye",
      "priority": 9,
      "keywords": ["謝謝", "先這樣", "再見", "bye", "結束", "好了"],
      "excludeKeywords": [],
      "contextKeywords": []
    },
    {
      "id": "greeting",
      "priority": 10,
      "keywords": ["嗨", "你好", "在嗎", "哈囉", "hello", "hi"],
      "excludeKeywords": [],
      "contextKeywords": [],
      "specialConditions": {
        "shortMessage": true,
        "shortMessageThreshold": 5
      }
    },
    {
      "id": "service_inquiry",
      "priority": 11,
      "keywords": ["拍", "照", "形象", "證件", "寫真", "全家福", "工作坊"],
      "excludeKeywords": [],
      "contextKeywords": []
    }
  ],
  "fallback": {
    "useContextIntent": true,
    "contextIntentThreshold": 10,
    "defaultIntent": "service_inquiry"
  }
}

